LICENSE
MANIFEST.in
README.rst
setup.cfg
setup.py
versioneer.py
artellapipe/__init__.py
artellapipe/tools/__init__.py
artellapipe/tools/namemanager/__init__.py
artellapipe/tools/namemanager/__logging__.ini
artellapipe/tools/namemanager/__version__.py
artellapipe/tools/namemanager/_version.py
artellapipe/tools/namemanager/core/__init__.py
artellapipe/tools/namemanager/core/namemanager.py
artellapipe/tools/namemanager/resources/icons/color/rename.png
artellapipe/tools/namemanager/resources/images/namemanager_logo.png
artellapipe/tools/namemanager/widgets/__init__.py
artellapipe/tools/namemanager/widgets/namemanager.py
artellapipe_tools_namemanager.egg-info/PKG-INFO
artellapipe_tools_namemanager.egg-info/SOURCES.txt
artellapipe_tools_namemanager.egg-info/dependency_links.txt
artellapipe_tools_namemanager.egg-info/not-zip-safe
artellapipe_tools_namemanager.egg-info/requires.txt
artellapipe_tools_namemanager.egg-info/top_level.txt
tests/__init__.py
tests/test_general.py