Metadata-Version: 2.1
Name: artellapipe-tools-namemanager
Version: 0.0.9
Summary: Tool to manage the nomenclature of the project
Home-page: https://github.com/ArtellaPipe/artellapipe-tools-namemanager
Author: Tomas Poveda
Author-email: tpovedatd@gmail.com
License: MIT
Platform: UNKNOWN
Provides-Extra: dev
Provides-Extra: test
